examples/__init__.py
examples/defining_orbits.py
examples/maneuvers.py
examples/misfire.py
examples/plotting.py
orbites/__init__.py
orbites/bodies.py
orbites/constants.py
orbites/elements.py
orbites/maneuver.py
orbites/plotting.py
orbites/utilities.py
orbit_pkg_SERGEI_DOLIN-0.0.0.dist-info/LICENSE
orbit_pkg_SERGEI_DOLIN-0.0.0.dist-info/METADATA
orbit_pkg_SERGEI_DOLIN-0.0.0.dist-info/WHEEL
orbit_pkg_SERGEI_DOLIN-0.0.0.dist-info/top_level.txt
orbit_pkg_SERGEI_DOLIN-0.0.0.dist-info/RECORD
