Metadata-Version: 2.1
Name: orbit-pkg-SERGEI-DOLIN
Version: 0.0.0
Summary: lib for edu
Home-page: https://github.com/SergeyDolin/Orbit
Author: Frazer McLean
Author-email: frazer@frazermclean.co.uk
License: UNKNOWN
Platform: UNKNOWN
Classifier: Programming Language :: Python :: 3
Classifier: License :: OSI Approved :: MIT License
Classifier: Operating System :: OS Independent
Requires-Python: >=3.8
License-File: LICENSE
